odoo10_addon_account_bank_statement_import_move_line-10.0.1.0.0-py2.7-nspkg.pth
odoo/addons/account_bank_statement_import_move_line/README.rst
odoo/addons/account_bank_statement_import_move_line/__init__.py
odoo/addons/account_bank_statement_import_move_line/__manifest__.py
odoo/addons/account_bank_statement_import_move_line/i18n/es.po
odoo/addons/account_bank_statement_import_move_line/models/__init__.py
odoo/addons/account_bank_statement_import_move_line/models/account_move_line.py
odoo/addons/account_bank_statement_import_move_line/static/description/icon.png
odoo/addons/account_bank_statement_import_move_line/tests/__init__.py
odoo/addons/account_bank_statement_import_move_line/tests/test_account_bank_statement_import_move_line.py
odoo/addons/account_bank_statement_import_move_line/views/account_bank_statement_view.xml
odoo/addons/account_bank_statement_import_move_line/wizards/__init__.py
odoo/addons/account_bank_statement_import_move_line/wizards/account_statement_line_create.py
odoo/addons/account_bank_statement_import_move_line/wizards/account_statement_line_create_view.xml
odoo10_addon_account_bank_statement_import_move_line-10.0.1.0.0.dist-info/DESCRIPTION.rst
odoo10_addon_account_bank_statement_import_move_line-10.0.1.0.0.dist-info/METADATA
odoo10_addon_account_bank_statement_import_move_line-10.0.1.0.0.dist-info/RECORD
odoo10_addon_account_bank_statement_import_move_line-10.0.1.0.0.dist-info/WHEEL
odoo10_addon_account_bank_statement_import_move_line-10.0.1.0.0.dist-info/metadata.json
odoo10_addon_account_bank_statement_import_move_line-10.0.1.0.0.dist-info/namespace_packages.txt
odoo10_addon_account_bank_statement_import_move_line-10.0.1.0.0.dist-info/top_level.txt
